otp/cli.py
simple_totp-1.1.0.dist-info/LICENSE
simple_totp-1.1.0.dist-info/METADATA
simple_totp-1.1.0.dist-info/WHEEL
simple_totp-1.1.0.dist-info/entry_points.txt
simple_totp-1.1.0.dist-info/top_level.txt
simple_totp-1.1.0.dist-info/RECORD
