Metadata-Version: 2.1
Name: simple-totp
Version: 1.1.0
Summary: A simple TOTP CLI
Home-page: https://github.com/chunkhang/simple-totp
Author: Marcus Mu
Author-email: chunkhang@gmail.com
License: UNKNOWN
Platform: UNKNOWN
Classifier: Programming Language :: Python :: 3
Classifier: License :: OSI Approved :: MIT License
Classifier: Operating System :: OS Independent
Requires-Python: >=3
Requires-Dist: pyotp (>=2.6.0)
Requires-Dist: PyYAML (>=5.4.1)
